corny_commons/__init__.py
corny_commons/console_graphics.py
corny_commons/file_manager.py
corny_commons/util/__init__.py
corny_commons/util/currency.py
corny_commons/util/polish.py
corny_commons/util/web.py
corny_commons-1.0.2.dist-info/LICENSE
corny_commons-1.0.2.dist-info/METADATA
corny_commons-1.0.2.dist-info/WHEEL
corny_commons-1.0.2.dist-info/top_level.txt
corny_commons-1.0.2.dist-info/RECORD
