Metadata-Version: 2.1
Name: corny-commons
Version: 1.0.2
Summary: A project containing packages common to various other Python projects.
Author-email: Konrad Guzek <konrad@guzek.uk>
License:                     GNU AFFERO GENERAL PUBLIC LICENSE
Project-URL: Homepage, https://github.com/kguzek/corny-commons
Project-URL: Bug Tracker, https://github.com/kguzek/corny-commons/issues
Classifier: Programming Language :: Python :: 3
Classifier: License :: OSI Approved :: MIT License
Classifier: Operating System :: OS Independent
Requires-Python: >=3.7
License-File: LICENSE
Requires-Dist: requests
